Aplicacion_ventas/Descuentos.py
Aplicacion_ventas/Exceptions.py
Aplicacion_ventas/Gestor_ventas.py
Aplicacion_ventas/Impuestos.py
Aplicacion_ventas/Precios.py
Aplicacion_ventas/__init__.py
Tests/Test_aplicacion_ventas.py
Tests/__init__.py
aplicacion_ventas_dmendozag-0.1.0.dist-info/licenses/LICENSE
aplicacion_ventas_dmendozag-0.1.0.dist-info/METADATA
aplicacion_ventas_dmendozag-0.1.0.dist-info/WHEEL
aplicacion_ventas_dmendozag-0.1.0.dist-info/top_level.txt
aplicacion_ventas_dmendozag-0.1.0.dist-info/RECORD
