Metadata-Version: 2.4
Name: aplicacion_ventas_dmendozag
Version: 0.1.0
Summary: Paquetes para gestionar ventas, precios, impuestos y descuentos
Author: Diego Mendoza
Author-email: diegomendozagarcia@gmail.com
Classifier: Programming Language :: Python :: 3
Classifier: License :: OSI Approved :: MIT License
Classifier: Operating System :: OS Independent
Requires-Python: >=3.6
License-File: LICENSE
Dynamic: author
Dynamic: author-email
Dynamic: classifier
Dynamic: description
Dynamic: description-content-type
Dynamic: license-file
Dynamic: requires-python
Dynamic: summary
